feltoken/__init__.py
feltoken/__main__.py
feltoken/config.py
feltoken/typing.py
feltoken/algorithm/__init__.py
feltoken/algorithm/aggregate.py
feltoken/algorithm/train.py
feltoken/core/__init__.py
feltoken/core/aggregation.py
feltoken/core/cryptography.py
feltoken/core/data.py
feltoken/core/ocean.py
feltoken/core/prompts.py
feltoken/core/sklearn_to_json.py
feltoken/core/storage.py
feltoken/core/training.py
tests/__init__.py
tests/test_aggregation.py
tests/test_cryptography.py
tests/test_sklearn_to_json.py
tests/test_training.py
feltoken-0.2.2.dist-info/LICENSE
feltoken-0.2.2.dist-info/METADATA
feltoken-0.2.2.dist-info/WHEEL
feltoken-0.2.2.dist-info/entry_points.txt
feltoken-0.2.2.dist-info/top_level.txt
feltoken-0.2.2.dist-info/RECORD
