Metadata-Version: 2.1
Name: feltoken
Version: 0.2.2
Summary: FELToken python package intended for running federated learning on Ocean protocol.
Home-page: https://feltoken.ai/
Author: FELToken
Maintainer: FELToken
Maintainer-email: info@bretahajek.com
License: GPL-3.0 License
Project-URL: Bug Tracker, https://github.com/FELToken/feltoken.py/issues
Project-URL: Documentation, https://docs.feltoken.ai/
Project-URL: Source Code, https://github.com/FELToken/feltoken.py
Keywords: Federated Learning,Web3,Machine Learning
Platform: Windows
Platform: Linux
Platform: Solaris
Platform: Mac OS-X
Platform: Unix
Classifier: Intended Audience :: Science/Research
Classifier: Intended Audience :: Developers
Classifier: Programming Language :: Python
Classifier: Programming Language :: Python :: 3
Classifier: Programming Language :: Python :: 3.8
Classifier: Programming Language :: Python :: 3.9
Classifier: Programming Language :: Python :: 3.10
Classifier: Programming Language :: Python :: 3 :: Only
Classifier: Topic :: Scientific/Engineering
Requires-Python: >=3.8
License-File: LICENSE
Requires-Dist: numpy (==1.21.0)
Requires-Dist: PyNaCl (==1.5.0)
Requires-Dist: scikit-learn (==1.0.1)
